ScreenX/__init__.py
ScreenX/_dividentifiers.py
ScreenX/bots.py
ScreenX-0.0.6.dist-info/LICENSE.txt
ScreenX-0.0.6.dist-info/METADATA
ScreenX-0.0.6.dist-info/WHEEL
ScreenX-0.0.6.dist-info/top_level.txt
ScreenX-0.0.6.dist-info/RECORD
