Metadata-Version: 2.1
Name: ScreenX
Version: 0.0.6
Summary: The Ultimate AI-Powered Web Automation & Scraping Bot
Home-page: UNKNOWN
Author: David C
Author-email: structureddatadrive@gmail.com
License: MIT
Platform: UNKNOWN
Classifier: License :: OSI Approved :: MIT License
Classifier: Programming Language :: Python :: 3
Classifier: Operating System :: OS Independent
Requires-Python: >=3.6
License-File: LICENSE.txt
Requires-Dist: selenium >=4.24.0
Requires-Dist: pandas >=2.2.2
Provides-Extra: dev
Requires-Dist: pytest >=7.0 ; extra == 'dev'
Requires-Dist: twine >=4.0.2 ; extra == 'dev'
